scitokens/__init__.py
scitokens/scitokens.py
scitokens/urltools.py
scitokens/tools/__init__.py
scitokens/tools/admin_create_key.py
scitokens/tools/admin_create_token.py
scitokens/tools/verify_token.py
scitokens/utils/__init__.py
scitokens/utils/config.py
scitokens/utils/demo.py
scitokens/utils/errors.py
scitokens/utils/keycache.py
scitokens/utils/scitokens_protect.py
scitokens-1.8.1.dist-info/LICENSE
scitokens-1.8.1.dist-info/METADATA
scitokens-1.8.1.dist-info/WHEEL
scitokens-1.8.1.dist-info/entry_points.txt
scitokens-1.8.1.dist-info/top_level.txt
scitokens-1.8.1.dist-info/RECORD
