Metadata-Version: 2.1
Name: scitokens
Version: 1.8.1
Summary: SciToken reference implementation library
Home-page: https://scitokens.org
Author: Brian Bockelman
Author-email: team@scitokens.org
License: Apache-2.0
Project-URL: Documentation, https://scitokens.readthedocs.io/
Project-URL: Issue Tracker, https://github.com/scitokens/scitokens/issues
Project-URL: Source Code, https://github.com/scitokens/scitokens
Classifier: Development Status :: 5 - Production/Stable
Classifier: License :: OSI Approved :: Apache Software License
Classifier: Natural Language :: English
Classifier: Operating System :: OS Independent
Classifier: Programming Language :: Python
Classifier: Programming Language :: Python :: 3.5
Classifier: Programming Language :: Python :: 3.6
Classifier: Programming Language :: Python :: 3.7
Classifier: Programming Language :: Python :: 3.8
Classifier: Programming Language :: Python :: 3.9
Classifier: Programming Language :: Python :: 3.10
Classifier: Topic :: Scientific/Engineering
Requires-Python: >=3.5
Provides-Extra: docs
License-File: LICENSE
